callbackin/__init__.py
callbackin/__main__.py
callbackin/handler/__init__.py
callbackin/handler/callback.py
callbackin/handler/login.py
callbackin/main.py
callbackin/schemas/__init__.py
callbackin/schemas/callback.py
callbackin/utils/__init__.py
callbackin/utils/config.py
callbackin/utils/request.py
callbackin-0.9.0.dist-info/METADATA
callbackin-0.9.0.dist-info/WHEEL
callbackin-0.9.0.dist-info/entry_points.txt
callbackin-0.9.0.dist-info/RECORD
