Metadata-Version: 2.1
Name: callbackin
Version: 0.9.0
Summary: 
Author: ibrahim4529
Author-email: ibrahim.hanif4529@gmail.com
Requires-Python: >=3.10,<4.0
Classifier: Programming Language :: Python :: 3
Classifier: Programming Language :: Python :: 3.10
Classifier: Programming Language :: Python :: 3.11
Requires-Dist: paho-mqtt (>=1.6.1,<2.0.0)
Requires-Dist: requests (>=2.31.0,<3.0.0)
Requires-Dist: rich (>=13.4.2,<14.0.0)
Requires-Dist: typer[all] (>=0.9.0,<0.10.0)
